jipubetapi
