Metadata-Version: 2.1
Name: jipubetapi
Version: 0.0.3
Summary: This library makes it easier to access the API
Home-page: https://github.com/DmitriyUsername/jipubetapi-lib/
Author: Dmitrii Kazanin
Author-email: dmitriikazanin@gmail.com
License: UNKNOWN
Download-URL: https://github.com/DmitriyUsername/jipubetapi-lib/archive/main.zip
Platform: UNKNOWN
Classifier: Programming Language :: Python :: 3.7
Classifier: License :: OSI Approved :: GNU General Public License v3 (GPLv3)
